mindlogger_data_export/__init__.py
mindlogger_data_export/__main__.py
mindlogger_data_export/config.py
mindlogger_data_export/main.py
mindlogger_data_export/mindlogger.py
mindlogger_data_export/models.py
mindlogger_data_export/outputs.py
mindlogger_data_export/parsers.py
mindlogger_data_export/processors.py
mindlogger_data_export/schema.py
mindlogger_data_export/util.py
mindlogger_data_export/writers.py
mindlogger_data_export-0.1.10.dist-info/METADATA
mindlogger_data_export-0.1.10.dist-info/WHEEL
mindlogger_data_export-0.1.10.dist-info/entry_points.txt
mindlogger_data_export-0.1.10.dist-info/RECORD
