Metadata-Version: 2.4
Name: mindlogger-data-export
Version: 0.1.10
Summary: Add your description here
Author-email: Gabriel Schubiner <gabriel.schubiner@childmind.org>
Requires-Python: >=3.11
Requires-Dist: lark>=1.2.2
Requires-Dist: packaging>=24.2
Requires-Dist: polars>=1.31.0
Requires-Dist: tyro>=0.9.5
Requires-Dist: xlsxwriter>=3.2.5
